quantpycython/__init__.py
quantpycython/conftest.py
quantpycython/release.py
quantpycython-0.0.2.dev1.dist-info/DESCRIPTION.rst
quantpycython-0.0.2.dev1.dist-info/METADATA
quantpycython-0.0.2.dev1.dist-info/RECORD
quantpycython-0.0.2.dev1.dist-info/WHEEL
quantpycython-0.0.2.dev1.dist-info/metadata.json
quantpycython-0.0.2.dev1.dist-info/top_level.txt
